<?xml version="1.0" encoding="UTF-8" standalone="no"?>
<annotation>
    <folder>NA</folder>
    <filename>A3-1.jpg</filename>
    <source>
        <database>Unknown</database>
    </source>
    <size>
        <width>3072</width>
        <height>2048</height>
        <depth>3</depth>
    </size>
    <segmented>0</segmented>
    <object>
        <name>glue</name>
        <pose>Unspecified</pose>
        <truncated>0</truncated>
        <difficult>0</difficult>
        <occluded>0</occluded>
        <bndbox>
            <xmin>2136</xmin>
            <ymin>1184</ymin>
            <xmax>2163</xmax>
            <ymax>1216</ymax>
        </bndbox>
    </object>
    <object>
        <name>glue</name>
        <pose>Unspecified</pose>
        <truncated>0</truncated>
        <difficult>0</difficult>
        <occluded>0</occluded>
        <bndbox>
            <xmin>1926</xmin>
            <ymin>1236</ymin>
            <xmax>1952</xmax>
            <ymax>1267</ymax>
        </bndbox>
    </object>
    <object>
        <name>glue</name>
        <pose>Unspecified</pose>
        <truncated>0</truncated>
        <difficult>0</difficult>
        <occluded>0</occluded>
        <bndbox>
            <xmin>2226</xmin>
            <ymin>1366</ymin>
            <xmax>2247</xmax>
            <ymax>1387</ymax>
        </bndbox>
    </object>
    <object>
        <name>glue</name>
        <pose>Unspecified</pose>
        <truncated>0</truncated>
        <difficult>0</difficult>
        <occluded>0</occluded>
        <bndbox>
            <xmin>2220</xmin>
            <ymin>1350</ymin>
            <xmax>2231</xmax>
            <ymax>1362</ymax>
        </bndbox>
    </object>
    <object>
        <name>glue</name>
        <pose>Unspecified</pose>
        <truncated>0</truncated>
        <difficult>0</difficult>
        <occluded>0</occluded>
        <bndbox>
            <xmin>1761</xmin>
            <ymin>1446</ymin>
            <xmax>1777</xmax>
            <ymax>1466</ymax>
        </bndbox>
    </object>
    <object>
        <name>injection_hole</name>
        <pose>Unspecified</pose>
        <truncated>0</truncated>
        <difficult>0</difficult>
        <occluded>0</occluded>
        <bndbox>
            <xmin>924</xmin>
            <ymin>1318</ymin>
            <xmax>969</xmax>
            <ymax>1380</ymax>
        </bndbox>
    </object>
    <object>
        <name>injection_hole</name>
        <pose>Unspecified</pose>
        <truncated>0</truncated>
        <difficult>0</difficult>
        <occluded>0</occluded>
        <bndbox>
            <xmin>2158</xmin>
            <ymin>1307</ymin>
            <xmax>2206</xmax>
            <ymax>1385</ymax>
        </bndbox>
    </object>
</annotation>
